sha256sumf/__init__.py
sha256sumf/__main__.py
sha256sumf/sha256sumf.py
sha256sumf-1.0.1.dist-info/LICENSE
sha256sumf-1.0.1.dist-info/METADATA
sha256sumf-1.0.1.dist-info/WHEEL
sha256sumf-1.0.1.dist-info/entry_points.txt
sha256sumf-1.0.1.dist-info/top_level.txt
sha256sumf-1.0.1.dist-info/RECORD
