Metadata-Version: 2.1
Name: sha256sumf
Version: 1.0.1
Summary: sha256sum for folders
Home-page: https://github.com/bimbashrestha/sha256sumf
Author: Bimba Shrestha
License: UNKNOWN
Platform: UNKNOWN
